diaspora_auth_provider.py
synapse_diaspora_auth-0.2.2.dist-info/LICENSE
synapse_diaspora_auth-0.2.2.dist-info/METADATA
synapse_diaspora_auth-0.2.2.dist-info/WHEEL
synapse_diaspora_auth-0.2.2.dist-info/top_level.txt
synapse_diaspora_auth-0.2.2.dist-info/RECORD
