Metadata-Version: 2.1
Name: synapse-diaspora-auth
Version: 0.2.2
Summary: A Diaspora* auth provider for Synapse
Home-page: UNKNOWN
Author: Shamil K
Author-email: noteness@riseup.net
License: GPLv3
Keywords: matrix synapse diaspora authentication
Platform: UNKNOWN
Classifier: Development Status :: 5 - Production/Stable
Classifier: License :: OSI Approved :: GNU General Public License v3 or later (GPLv3+)
Classifier: Programming Language :: Python :: 2.7
Classifier: Topic :: Communications :: Chat
Requires-Dist: Twisted (>=15.1.0)
Requires-Dist: psycopg2
Requires-Dist: bcrypt
Requires-Dist: pymysql
